games/__init__.py
games/adventure.py
games/chess.py
games/main.py
games/sudoku.py
games/tictactoe.py
t_games-1.0.7.dist-info/licenses/LICENSE
t_games-1.0.7.dist-info/METADATA
t_games-1.0.7.dist-info/WHEEL
t_games-1.0.7.dist-info/entry_points.txt
t_games-1.0.7.dist-info/top_level.txt
t_games-1.0.7.dist-info/RECORD
