Metadata-Version: 2.4
Name: t-games
Version: 1.0.7
Summary: A collection of classic games playable in your terminal
Home-page: https://github.com/pavansai-tanguturi/t-games
Author: Pavan Sai Tanguturi, Siddartha Karumuri
Author-email: PavanSai Tanguturi <pavansaitanguturi@gmail.com>, Siddartha Karumuri <siddarthakarumuri003@gmail.com>
License: MIT
Project-URL: Homepage, https://github.com/pavansai-tanguturi/t-games
Project-URL: Bug Reports, https://github.com/pavansai-tanguturi/t-games/issues
Project-URL: Source Code, https://github.com/pavansai-tanguturi/t-games
Keywords: games,terminal,console,multiplayer,chess,sudoku,tictactoe,adventure
Classifier: Development Status :: 4 - Beta
Classifier: Intended Audience :: End Users/Desktop
Classifier: Topic :: Games/Entertainment
Classifier: License :: OSI Approved :: MIT License
Classifier: Programming Language :: Python :: 3
Classifier: Programming Language :: Python :: 3.7
Classifier: Programming Language :: Python :: 3.8
Classifier: Programming Language :: Python :: 3.9
Classifier: Programming Language :: Python :: 3.10
Classifier: Programming Language :: Python :: 3.11
Classifier: Operating System :: OS Independent
Requires-Python: >=3.7
License-File: LICENSE
Requires-Dist: python-chess>=1.9.0
Dynamic: author
Dynamic: home-page
Dynamic: license-file
Dynamic: requires-python
